{
  "data": {
    "article": {},
    "attachments": {},
    "author_id": "1967234748704862208",
    "conversation_id": "2066463293871673641",
    "created_at": "2026-06-15T13:55:19.000Z",
    "edit_controls": {
      "editable_until": "2026-06-15T14:55:19.000Z",
      "edits_remaining": 5,
      "is_edit_eligible": false
    },
    "edit_history_tweet_ids": [
      "2066519927981478139"
    ],
    "entities": {
      "mentions": [
        {
          "end": 13,
          "id": "1648328293643599875",
          "start": 0,
          "username": "wngxur021212"
        }
      ]
    },
    "geo": {},
    "id": "2066519927981478139",
    "in_reply_to_user_id": "1648328293643599875",
    "lang": "ja",
    "note_tweet": {
      "entities": {}
    },
    "possibly_sensitive": false,
    "public_metrics": {
      "bookmark_count": 0,
      "impression_count": 0,
      "like_count": 0,
      "quote_count": 0,
      "reply_count": 0,
      "retweet_count": 0
    },
    "referenced_tweets": [
      {
        "id": "2066514129050030418",
        "type": "replied_to"
      }
    ],
    "reply_settings": "everyone",
    "text": "@wngxur021212 好！"
  },
  "includes": {
    "tweets": [
      {
        "article": {},
        "attachments": {},
        "author_id": "1967234748704862208",
        "conversation_id": "2066463293871673641",
        "created_at": "2026-06-15T13:55:19.000Z",
        "edit_controls": {
          "editable_until": "2026-06-15T14:55:19.000Z",
          "edits_remaining": 5,
          "is_edit_eligible": false
        },
        "edit_history_tweet_ids": [
          "2066519927981478139"
        ],
        "entities": {
          "mentions": [
            {
              "end": 13,
              "id": "1648328293643599875",
              "start": 0,
              "username": "wngxur021212"
            }
          ]
        },
        "geo": {},
        "id": "2066519927981478139",
        "in_reply_to_user_id": "1648328293643599875",
        "lang": "ja",
        "note_tweet": {
          "entities": {}
        },
        "possibly_sensitive": false,
        "public_metrics": {
          "bookmark_count": 0,
          "impression_count": 0,
          "like_count": 0,
          "quote_count": 0,
          "reply_count": 0,
          "retweet_count": 0
        },
        "referenced_tweets": [
          {
            "id": "2066514129050030418",
            "type": "replied_to"
          }
        ],
        "reply_settings": "everyone",
        "text": "@wngxur021212 好！"
      },
      {
        "article": {},
        "attachments": {},
        "author_id": "1648328293643599875",
        "conversation_id": "2066463293871673641",
        "created_at": "2026-06-15T13:32:16.000Z",
        "edit_controls": {
          "editable_until": "2026-06-15T14:32:16.000Z",
          "edits_remaining": 5,
          "is_edit_eligible": false
        },
        "edit_history_tweet_ids": [
          "2066514129050030418"
        ],
        "entities": {
          "mentions": [
            {
              "end": 10,
              "id": "1967234748704862208",
              "start": 0,
              "username": "yuri__ono"
            }
          ]
        },
        "geo": {},
        "id": "2066514129050030418",
        "in_reply_to_user_id": "1967234748704862208",
        "lang": "zh",
        "note_tweet": {
          "entities": {}
        },
        "possibly_sensitive": false,
        "public_metrics": {
          "bookmark_count": 0,
          "impression_count": 14,
          "like_count": 0,
          "quote_count": 0,
          "reply_count": 1,
          "retweet_count": 0
        },
        "referenced_tweets": [
          {
            "id": "2066463293871673641",
            "type": "replied_to"
          }
        ],
        "reply_settings": "everyone",
        "text": "@yuri__ono 宝宝可以互fo！！"
      }
    ],
    "users": [
      {
        "created_at": "2025-09-14T14:31:42.000Z",
        "description": "欢迎互fo 当朋友圈刷 发碎碎念 什么都看  只和熟人加v 不聊黄 喜欢有礼貌的人 看到的基本上都回 欢迎找我聊天呀 发泄号@Yuri__ovo",
        "entities": {
          "description": {
            "mentions": [
              {
                "end": 72,
                "start": 62,
                "username": "Yuri__ovo"
              }
            ]
          }
        },
        "id": "1967234748704862208",
        "location": "你又来看我啦(*･ω･)ﾉ 今天开心吗",
        "name": "yuri",
        "pinned_tweet_id": "2020195394265969020",
        "profile_image_url": "https://pbs.twimg.com/profile_images/2061096463300722689/xs50LU9B_normal.jpg",
        "protected": false,
        "public_metrics": {
          "followers_count": 773,
          "following_count": 705,
          "like_count": 5020,
          "listed_count": 1,
          "media_count": 70,
          "tweet_count": 1670
        },
        "username": "yuri__ono",
        "verified": false
      },
      {
        "created_at": "2023-04-18T14:11:14.000Z",
        "description": "你好不好｜🚪52｜4i/1i｜女宝可以互fo｜不打游戏",
        "id": "1648328293643599875",
        "location": "乌托邦",
        "name": "那你全都说出来",
        "pinned_tweet_id": "2066443872062865846",
        "profile_image_url": "https://pbs.twimg.com/profile_images/2064210984172957696/Aqvntixv_normal.jpg",
        "protected": false,
        "public_metrics": {
          "followers_count": 305,
          "following_count": 58,
          "like_count": 234,
          "listed_count": 0,
          "media_count": 19,
          "tweet_count": 232
        },
        "username": "wngxur021212",
        "verified": false
      }
    ]
  }
}