{
  "data": {
    "article": {},
    "attachments": {},
    "author_id": "1967234748704862208",
    "conversation_id": "2058374372168225041",
    "created_at": "2026-05-24T14:12:21.000Z",
    "edit_controls": {
      "editable_until": "2026-05-24T15:12:21.000Z",
      "edits_remaining": 5,
      "is_edit_eligible": false
    },
    "edit_history_tweet_ids": [
      "2058551681642795356"
    ],
    "entities": {
      "mentions": [
        {
          "end": 12,
          "id": "1921889756788719616",
          "start": 0,
          "username": "sumo2113144"
        }
      ]
    },
    "geo": {},
    "id": "2058551681642795356",
    "in_reply_to_user_id": "1921889756788719616",
    "lang": "zh",
    "note_tweet": {
      "entities": {}
    },
    "possibly_sensitive": false,
    "public_metrics": {
      "bookmark_count": 0,
      "impression_count": 0,
      "like_count": 0,
      "quote_count": 0,
      "reply_count": 0,
      "retweet_count": 0
    },
    "referenced_tweets": [
      {
        "id": "2058479762377703433",
        "type": "replied_to"
      }
    ],
    "reply_settings": "everyone",
    "text": "@sumo2113144 我服啦"
  },
  "includes": {
    "tweets": [
      {
        "article": {},
        "attachments": {},
        "author_id": "1967234748704862208",
        "conversation_id": "2058374372168225041",
        "created_at": "2026-05-24T14:12:21.000Z",
        "edit_controls": {
          "editable_until": "2026-05-24T15:12:21.000Z",
          "edits_remaining": 5,
          "is_edit_eligible": false
        },
        "edit_history_tweet_ids": [
          "2058551681642795356"
        ],
        "entities": {
          "mentions": [
            {
              "end": 12,
              "id": "1921889756788719616",
              "start": 0,
              "username": "sumo2113144"
            }
          ]
        },
        "geo": {},
        "id": "2058551681642795356",
        "in_reply_to_user_id": "1921889756788719616",
        "lang": "zh",
        "note_tweet": {
          "entities": {}
        },
        "possibly_sensitive": false,
        "public_metrics": {
          "bookmark_count": 0,
          "impression_count": 0,
          "like_count": 0,
          "quote_count": 0,
          "reply_count": 0,
          "retweet_count": 0
        },
        "referenced_tweets": [
          {
            "id": "2058479762377703433",
            "type": "replied_to"
          }
        ],
        "reply_settings": "everyone",
        "text": "@sumo2113144 我服啦"
      },
      {
        "article": {},
        "attachments": {},
        "author_id": "1921889756788719616",
        "conversation_id": "2058374372168225041",
        "created_at": "2026-05-24T09:26:34.000Z",
        "edit_controls": {
          "editable_until": "2026-05-24T10:26:34.000Z",
          "edits_remaining": 5,
          "is_edit_eligible": false
        },
        "edit_history_tweet_ids": [
          "2058479762377703433"
        ],
        "entities": {
          "mentions": [
            {
              "end": 10,
              "id": "1967234748704862208",
              "start": 0,
              "username": "yuri__ono"
            }
          ]
        },
        "geo": {},
        "id": "2058479762377703433",
        "in_reply_to_user_id": "1967234748704862208",
        "lang": "zh",
        "note_tweet": {
          "entities": {}
        },
        "possibly_sensitive": false,
        "public_metrics": {
          "bookmark_count": 0,
          "impression_count": 18,
          "like_count": 0,
          "quote_count": 0,
          "reply_count": 0,
          "retweet_count": 0
        },
        "referenced_tweets": [
          {
            "id": "2058374372168225041",
            "type": "replied_to"
          }
        ],
        "reply_settings": "everyone",
        "text": "@yuri__ono 所以我很想去把我名字改了，然后再真名上网（一切尴尬都来源于名字不好听）"
      }
    ],
    "users": [
      {
        "created_at": "2025-09-14T14:31:42.000Z",
        "description": "欢迎互fo 当朋友圈刷 发碎碎念 什么都看 互关可以加微信 不聊黄 喜欢有礼貌的人 看到的基本上都回 欢迎找我聊天呀 发泄号@Yuri__ovo",
        "entities": {
          "description": {
            "mentions": [
              {
                "end": 72,
                "start": 62,
                "username": "Yuri__ovo"
              }
            ]
          }
        },
        "id": "1967234748704862208",
        "location": "你又来看我啦(*･ω･)ﾉ",
        "name": "yuri",
        "pinned_tweet_id": "2020195394265969020",
        "profile_image_url": "https://pbs.twimg.com/profile_images/1971968133637591045/valSqUne_normal.jpg",
        "protected": false,
        "public_metrics": {
          "followers_count": 184,
          "following_count": 422,
          "like_count": 4230,
          "listed_count": 0,
          "media_count": 45,
          "tweet_count": 1070
        },
        "username": "yuri__ono",
        "verified": false
      },
      {
        "created_at": "2025-05-12T11:26:49.000Z",
        "description": "intp版🍃",
        "id": "1921889756788719616",
        "location": "m78星云",
        "name": "树叶子",
        "profile_image_url": "https://pbs.twimg.com/profile_images/2036566136947662848/RlzpWwyK_normal.jpg",
        "protected": false,
        "public_metrics": {
          "followers_count": 138,
          "following_count": 74,
          "like_count": 1104,
          "listed_count": 1,
          "media_count": 25,
          "tweet_count": 1249
        },
        "username": "sumo2113144",
        "verified": false
      }
    ]
  }
}