{
  "data": {
    "article": {},
    "attachments": {
      "media_keys": [
        "3_2070098500558209024"
      ],
      "media_source_tweet_id": [
        "2070098510498721942"
      ]
    },
    "author_id": "1967234748704862208",
    "conversation_id": "2070405926012809672",
    "created_at": "2026-06-26T07:16:53.000Z",
    "edit_controls": {
      "editable_until": "2026-06-26T08:16:53.000Z",
      "edits_remaining": 5,
      "is_edit_eligible": false
    },
    "edit_history_tweet_ids": [
      "2070405926012809672"
    ],
    "entities": {
      "mentions": [
        {
          "end": 17,
          "id": "3326305791",
          "start": 3,
          "username": "CuteCatsMagic"
        }
      ],
      "urls": [
        {
          "display_url": "pic.x.com/a0p8dNcPRC",
          "end": 42,
          "expanded_url": "https://x.com/CuteCatsMagic/status/2070098510498721942/photo/1",
          "media_key": "3_2070098500558209024",
          "start": 19,
          "url": "https://t.co/a0p8dNcPRC"
        }
      ]
    },
    "geo": {},
    "id": "2070405926012809672",
    "lang": "zxx",
    "note_tweet": {
      "entities": {}
    },
    "possibly_sensitive": false,
    "public_metrics": {
      "bookmark_count": 0,
      "impression_count": 0,
      "like_count": 0,
      "quote_count": 0,
      "reply_count": 0,
      "retweet_count": 461
    },
    "referenced_tweets": [
      {
        "id": "2070098510498721942",
        "type": "retweeted"
      }
    ],
    "reply_settings": "everyone",
    "text": "RT @CuteCatsMagic: https://t.co/a0p8dNcPRC"
  },
  "includes": {
    "media": [
      {
        "height": 1039,
        "media_key": "3_2070098500558209024",
        "public_metrics": {},
        "type": "photo",
        "url": "https://pbs.twimg.com/media/HLp3nk_XQAA97ty.jpg",
        "width": 736
      }
    ],
    "tweets": [
      {
        "article": {},
        "attachments": {
          "media_keys": [
            "3_2070098500558209024"
          ],
          "media_source_tweet_id": [
            "2070098510498721942"
          ]
        },
        "author_id": "1967234748704862208",
        "conversation_id": "2070405926012809672",
        "created_at": "2026-06-26T07:16:53.000Z",
        "edit_controls": {
          "editable_until": "2026-06-26T08:16:53.000Z",
          "edits_remaining": 5,
          "is_edit_eligible": false
        },
        "edit_history_tweet_ids": [
          "2070405926012809672"
        ],
        "entities": {
          "mentions": [
            {
              "end": 17,
              "id": "3326305791",
              "start": 3,
              "username": "CuteCatsMagic"
            }
          ],
          "urls": [
            {
              "display_url": "pic.x.com/a0p8dNcPRC",
              "end": 42,
              "expanded_url": "https://x.com/CuteCatsMagic/status/2070098510498721942/photo/1",
              "media_key": "3_2070098500558209024",
              "start": 19,
              "url": "https://t.co/a0p8dNcPRC"
            }
          ]
        },
        "geo": {},
        "id": "2070405926012809672",
        "lang": "zxx",
        "note_tweet": {
          "entities": {}
        },
        "possibly_sensitive": false,
        "public_metrics": {
          "bookmark_count": 0,
          "impression_count": 0,
          "like_count": 0,
          "quote_count": 0,
          "reply_count": 0,
          "retweet_count": 461
        },
        "referenced_tweets": [
          {
            "id": "2070098510498721942",
            "type": "retweeted"
          }
        ],
        "reply_settings": "everyone",
        "text": "RT @CuteCatsMagic: https://t.co/a0p8dNcPRC"
      },
      {
        "article": {},
        "attachments": {
          "media_keys": [
            "3_2070098500558209024"
          ]
        },
        "author_id": "3326305791",
        "conversation_id": "2070098510498721942",
        "created_at": "2026-06-25T10:55:20.000Z",
        "edit_controls": {
          "editable_until": "2026-06-25T11:55:20.000Z",
          "edits_remaining": 5,
          "is_edit_eligible": true
        },
        "edit_history_tweet_ids": [
          "2070098510498721942"
        ],
        "entities": {
          "urls": [
            {
              "display_url": "pic.x.com/a0p8dNcPRC",
              "end": 23,
              "expanded_url": "https://x.com/CuteCatsMagic/status/2070098510498721942/photo/1",
              "media_key": "3_2070098500558209024",
              "start": 0,
              "url": "https://t.co/a0p8dNcPRC"
            }
          ]
        },
        "geo": {},
        "id": "2070098510498721942",
        "lang": "zxx",
        "note_tweet": {
          "entities": {}
        },
        "possibly_sensitive": false,
        "public_metrics": {
          "bookmark_count": 165,
          "impression_count": 47494,
          "like_count": 6645,
          "quote_count": 11,
          "reply_count": 20,
          "retweet_count": 461
        },
        "reply_settings": "everyone",
        "text": "https://t.co/a0p8dNcPRC"
      }
    ],
    "users": [
      {
        "created_at": "2025-09-14T14:31:42.000Z",
        "description": "欢迎互fo 11年 当朋友圈刷 发碎碎念 什么都看 只和熟人加v 不聊黄 喜欢有礼貌的人 看到的基本上都回 欢迎找我聊天呀 发泄号@Yuri__ovo",
        "entities": {
          "description": {
            "mentions": [
              {
                "end": 75,
                "start": 65,
                "username": "Yuri__ovo"
              }
            ]
          }
        },
        "id": "1967234748704862208",
        "location": "你又来看我啦(*･ω･)ﾉ 今天开心吗",
        "name": "yuri",
        "pinned_tweet_id": "2020195394265969020",
        "profile_image_url": "https://pbs.twimg.com/profile_images/2061096463300722689/xs50LU9B_normal.jpg",
        "protected": false,
        "public_metrics": {
          "followers_count": 1245,
          "following_count": 861,
          "like_count": 5513,
          "listed_count": 1,
          "media_count": 87,
          "tweet_count": 2193
        },
        "url": "",
        "username": "yuri__ono",
        "verified": false
      },
      {
        "created_at": "2015-06-15T06:25:54.000Z",
        "description": "Cute cat videos 😺",
        "id": "3326305791",
        "name": "Cat 🐈",
        "pinned_tweet_id": "2069664431357763878",
        "profile_image_url": "https://pbs.twimg.com/profile_images/1801704006932123648/-ngn25vp_normal.jpg",
        "protected": false,
        "public_metrics": {
          "followers_count": 112426,
          "following_count": 17571,
          "like_count": 86057,
          "listed_count": 245,
          "media_count": 12037,
          "tweet_count": 51197
        },
        "url": "",
        "username": "CuteCatsMagic",
        "verified": true
      }
    ]
  }
}