{
  "data": {
    "article": {},
    "attachments": {
      "media_keys": [
        "3_2053367201944698880"
      ],
      "media_source_tweet_id": [
        "2053367210119455121"
      ]
    },
    "author_id": "1967234748704862208",
    "conversation_id": "2053490495469535728",
    "created_at": "2026-05-10T15:01:00.000Z",
    "edit_controls": {
      "editable_until": "2026-05-10T16:01:00.000Z",
      "edits_remaining": 5,
      "is_edit_eligible": false
    },
    "edit_history_tweet_ids": [
      "2053490495469535728"
    ],
    "entities": {
      "mentions": [
        {
          "end": 18,
          "id": "1991711672684421121",
          "start": 3,
          "username": "pearl0812lucky"
        }
      ],
      "urls": [
        {
          "display_url": "pic.x.com/0gtEDKK9Sh",
          "end": 59,
          "expanded_url": "https://x.com/pearl0812lucky/status/2053367210119455121/photo/1",
          "media_key": "3_2053367201944698880",
          "start": 36,
          "url": "https://t.co/0gtEDKK9Sh"
        }
      ]
    },
    "geo": {},
    "id": "2053490495469535728",
    "lang": "zh",
    "note_tweet": {
      "entities": {}
    },
    "possibly_sensitive": false,
    "public_metrics": {
      "bookmark_count": 0,
      "impression_count": 0,
      "like_count": 0,
      "quote_count": 0,
      "reply_count": 0,
      "retweet_count": 48
    },
    "referenced_tweets": [
      {
        "id": "2053367210119455121",
        "type": "retweeted"
      }
    ],
    "reply_settings": "everyone",
    "text": "RT @pearl0812lucky: 东亚小孩统一动物塑belike https://t.co/0gtEDKK9Sh"
  },
  "includes": {
    "media": [
      {
        "height": 1220,
        "media_key": "3_2053367201944698880",
        "public_metrics": {},
        "type": "photo",
        "url": "https://pbs.twimg.com/media/HH8Gl0laAAAeYtk.jpg",
        "width": 1206
      }
    ],
    "tweets": [
      {
        "article": {},
        "attachments": {
          "media_keys": [
            "3_2053367201944698880"
          ],
          "media_source_tweet_id": [
            "2053367210119455121"
          ]
        },
        "author_id": "1967234748704862208",
        "conversation_id": "2053490495469535728",
        "created_at": "2026-05-10T15:01:00.000Z",
        "edit_controls": {
          "editable_until": "2026-05-10T16:01:00.000Z",
          "edits_remaining": 5,
          "is_edit_eligible": false
        },
        "edit_history_tweet_ids": [
          "2053490495469535728"
        ],
        "entities": {
          "mentions": [
            {
              "end": 18,
              "id": "1991711672684421121",
              "start": 3,
              "username": "pearl0812lucky"
            }
          ],
          "urls": [
            {
              "display_url": "pic.x.com/0gtEDKK9Sh",
              "end": 59,
              "expanded_url": "https://x.com/pearl0812lucky/status/2053367210119455121/photo/1",
              "media_key": "3_2053367201944698880",
              "start": 36,
              "url": "https://t.co/0gtEDKK9Sh"
            }
          ]
        },
        "geo": {},
        "id": "2053490495469535728",
        "lang": "zh",
        "note_tweet": {
          "entities": {}
        },
        "possibly_sensitive": false,
        "public_metrics": {
          "bookmark_count": 0,
          "impression_count": 0,
          "like_count": 0,
          "quote_count": 0,
          "reply_count": 0,
          "retweet_count": 48
        },
        "referenced_tweets": [
          {
            "id": "2053367210119455121",
            "type": "retweeted"
          }
        ],
        "reply_settings": "everyone",
        "text": "RT @pearl0812lucky: 东亚小孩统一动物塑belike https://t.co/0gtEDKK9Sh"
      },
      {
        "article": {},
        "attachments": {
          "media_keys": [
            "3_2053367201944698880"
          ]
        },
        "author_id": "1991711672684421121",
        "conversation_id": "2053367210119455121",
        "created_at": "2026-05-10T06:51:07.000Z",
        "edit_controls": {
          "editable_until": "2026-05-10T07:51:07.000Z",
          "edits_remaining": 5,
          "is_edit_eligible": true
        },
        "edit_history_tweet_ids": [
          "2053367210119455121"
        ],
        "entities": {
          "urls": [
            {
              "display_url": "pic.x.com/0gtEDKK9Sh",
              "end": 39,
              "expanded_url": "https://x.com/pearl0812lucky/status/2053367210119455121/photo/1",
              "media_key": "3_2053367201944698880",
              "start": 16,
              "url": "https://t.co/0gtEDKK9Sh"
            }
          ]
        },
        "geo": {},
        "id": "2053367210119455121",
        "lang": "zh",
        "note_tweet": {
          "entities": {}
        },
        "possibly_sensitive": false,
        "public_metrics": {
          "bookmark_count": 34,
          "impression_count": 80022,
          "like_count": 1286,
          "quote_count": 12,
          "reply_count": 42,
          "retweet_count": 48
        },
        "reply_settings": "everyone",
        "text": "东亚小孩统一动物塑belike https://t.co/0gtEDKK9Sh"
      }
    ],
    "users": [
      {
        "created_at": "2025-09-14T14:31:42.000Z",
        "description": "欢迎互fo 当朋友圈刷 发碎碎念 什么都看 互关可以加微信 不聊黄 喜欢有礼貌的人 看到的基本上都回",
        "id": "1967234748704862208",
        "location": "你又来看我啦(*･ω･)ﾉ",
        "name": "yu ri",
        "pinned_tweet_id": "2020195394265969020",
        "profile_image_url": "https://pbs.twimg.com/profile_images/1971968133637591045/valSqUne_normal.jpg",
        "protected": false,
        "public_metrics": {
          "followers_count": 79,
          "following_count": 316,
          "like_count": 3153,
          "listed_count": 0,
          "media_count": 29,
          "tweet_count": 732
        },
        "username": "yuri__ono",
        "verified": false
      },
      {
        "created_at": "2025-11-21T03:34:11.000Z",
        "description": "日记本撕下来的废纸存放地   匿名https://t.co/KI0NDjJlXB",
        "entities": {
          "description": {
            "urls": [
              {
                "display_url": "ngl.link/orangecat60022",
                "end": 40,
                "expanded_url": "https://ngl.link/orangecat60022",
                "start": 17,
                "url": "https://t.co/KI0NDjJlXB"
              }
            ]
          }
        },
        "id": "1991711672684421121",
        "location": "欢迎打开我的文案收藏夹 （转载自微博、抖音、视频号、公众号）",
        "name": "orange cat",
        "pinned_tweet_id": "2009431887333486776",
        "profile_image_url": "https://pbs.twimg.com/profile_images/2003664682989522944/wMmqYGn__normal.jpg",
        "protected": false,
        "public_metrics": {
          "followers_count": 7214,
          "following_count": 66,
          "like_count": 7013,
          "listed_count": 7,
          "media_count": 158,
          "tweet_count": 1697
        },
        "username": "pearl0812lucky",
        "verified": false
      }
    ]
  }
}