{
  "data": {
    "article": {},
    "attachments": {},
    "author_id": "1967234748704862208",
    "conversation_id": "2047498324845224228",
    "created_at": "2026-04-24T15:07:07.000Z",
    "edit_controls": {
      "editable_until": "2026-04-24T16:07:07.000Z",
      "edits_remaining": 5,
      "is_edit_eligible": false
    },
    "edit_history_tweet_ids": [
      "2047693828967239910"
    ],
    "entities": {
      "mentions": [
        {
          "end": 16,
          "id": "1852895432269234176",
          "start": 0,
          "username": "432Ifantrygroup"
        }
      ]
    },
    "geo": {},
    "id": "2047693828967239910",
    "in_reply_to_user_id": "1852895432269234176",
    "lang": "zh",
    "note_tweet": {
      "entities": {}
    },
    "possibly_sensitive": false,
    "public_metrics": {
      "bookmark_count": 0,
      "impression_count": 0,
      "like_count": 0,
      "quote_count": 0,
      "reply_count": 0,
      "retweet_count": 0
    },
    "referenced_tweets": [
      {
        "id": "2047498324845224228",
        "type": "replied_to"
      }
    ],
    "reply_settings": "everyone",
    "text": "@432Ifantrygroup 这个感觉喝了好渴"
  },
  "includes": {
    "media": [
      {
        "height": 2048,
        "media_key": "3_2047498313843531776",
        "public_metrics": {},
        "type": "photo",
        "url": "https://pbs.twimg.com/media/HGos3kra4AAXcX1.jpg",
        "width": 1536
      }
    ],
    "tweets": [
      {
        "article": {},
        "attachments": {},
        "author_id": "1967234748704862208",
        "conversation_id": "2047498324845224228",
        "created_at": "2026-04-24T15:07:07.000Z",
        "edit_controls": {
          "editable_until": "2026-04-24T16:07:07.000Z",
          "edits_remaining": 5,
          "is_edit_eligible": false
        },
        "edit_history_tweet_ids": [
          "2047693828967239910"
        ],
        "entities": {
          "mentions": [
            {
              "end": 16,
              "id": "1852895432269234176",
              "start": 0,
              "username": "432Ifantrygroup"
            }
          ]
        },
        "geo": {},
        "id": "2047693828967239910",
        "in_reply_to_user_id": "1852895432269234176",
        "lang": "zh",
        "note_tweet": {
          "entities": {}
        },
        "possibly_sensitive": false,
        "public_metrics": {
          "bookmark_count": 0,
          "impression_count": 0,
          "like_count": 0,
          "quote_count": 0,
          "reply_count": 0,
          "retweet_count": 0
        },
        "referenced_tweets": [
          {
            "id": "2047498324845224228",
            "type": "replied_to"
          }
        ],
        "reply_settings": "everyone",
        "text": "@432Ifantrygroup 这个感觉喝了好渴"
      },
      {
        "article": {},
        "attachments": {
          "media_keys": [
            "3_2047498313843531776"
          ]
        },
        "author_id": "1852895432269234176",
        "context_annotations": [
          {
            "domain": {
              "description": "Categories within Brand Verticals that narrow down the scope of Brands",
              "id": "46",
              "name": "Business Taxonomy"
            },
            "entity": {
              "description": "Brands, companies, advertisers and every non-person handle with the profit intent and related to foods & beverages such as snacks, soft drinks, beers.",
              "id": "1557696888568045569",
              "name": "Food & Beverage Business"
            }
          }
        ],
        "conversation_id": "2047498324845224228",
        "created_at": "2026-04-24T02:10:15.000Z",
        "edit_controls": {
          "editable_until": "2026-04-24T03:10:15.000Z",
          "edits_remaining": 5,
          "is_edit_eligible": true
        },
        "edit_history_tweet_ids": [
          "2047498324845224228"
        ],
        "entities": {
          "urls": [
            {
              "display_url": "pic.x.com/3sorAJQT2K",
              "end": 49,
              "expanded_url": "https://x.com/432Ifantrygroup/status/2047498324845224228/photo/1",
              "media_key": "3_2047498313843531776",
              "start": 26,
              "url": "https://t.co/3sorAJQT2K"
            }
          ]
        },
        "geo": {},
        "id": "2047498324845224228",
        "lang": "zh",
        "note_tweet": {
          "entities": {}
        },
        "possibly_sensitive": false,
        "public_metrics": {
          "bookmark_count": 10,
          "impression_count": 30741,
          "like_count": 142,
          "quote_count": 1,
          "reply_count": 82,
          "retweet_count": 2
        },
        "reply_settings": "everyone",
        "text": "这玩意难喝死了，为什么你们都用这个送服那些药啊？？ https://t.co/3sorAJQT2K"
      }
    ],
    "users": [
      {
        "created_at": "2025-09-14T14:31:42.000Z",
        "description": "欢迎互fo 当朋友圈刷 发碎碎念 什么都看 互关可以加微信 不聊黄 喜欢有礼貌的人 看到的基本上都回",
        "id": "1967234748704862208",
        "location": "你又来看我啦(*･ω･)ﾉ",
        "name": "yu ri",
        "pinned_tweet_id": "2020195394265969020",
        "profile_image_url": "https://pbs.twimg.com/profile_images/1971968133637591045/valSqUne_normal.jpg",
        "protected": false,
        "public_metrics": {
          "followers_count": 70,
          "following_count": 307,
          "like_count": 2731,
          "listed_count": 0,
          "media_count": 28,
          "tweet_count": 630
        },
        "username": "yuri__ono",
        "verified": false
      },
      {
        "created_at": "2024-11-03T02:08:20.000Z",
        "description": "自由意志共产主义者，中国人，男。可以叫我东方或者东方白。\n会回关所有人",
        "id": "1852895432269234176",
        "name": "432InfantryRegiment",
        "pinned_tweet_id": "2047687487079014759",
        "profile_image_url": "https://pbs.twimg.com/profile_images/1900594696520691714/2Z7_CLpC_normal.jpg",
        "protected": false,
        "public_metrics": {
          "followers_count": 831,
          "following_count": 3220,
          "like_count": 27453,
          "listed_count": 3,
          "media_count": 297,
          "tweet_count": 7234
        },
        "username": "432Ifantrygroup",
        "verified": false
      }
    ]
  }
}