{
  "data": {
    "article": {},
    "attachments": {},
    "author_id": "1967234748704862208",
    "conversation_id": "2057162604854837441",
    "created_at": "2026-05-20T22:26:32.000Z",
    "edit_controls": {
      "editable_until": "2026-05-20T23:26:32.000Z",
      "edits_remaining": 5,
      "is_edit_eligible": false
    },
    "edit_history_tweet_ids": [
      "2057226496138420580"
    ],
    "entities": {
      "mentions": [
        {
          "end": 10,
          "id": "1944679199358570496",
          "start": 0,
          "username": "0kada_Mi0"
        }
      ]
    },
    "geo": {},
    "id": "2057226496138420580",
    "in_reply_to_user_id": "1944679199358570496",
    "lang": "zh",
    "note_tweet": {
      "entities": {}
    },
    "possibly_sensitive": false,
    "public_metrics": {
      "bookmark_count": 0,
      "impression_count": 0,
      "like_count": 0,
      "quote_count": 0,
      "reply_count": 0,
      "retweet_count": 0
    },
    "referenced_tweets": [
      {
        "id": "2057162604854837441",
        "type": "replied_to"
      }
    ],
    "reply_settings": "everyone",
    "text": "@0kada_Mi0 超级美 我好喜欢sasi这首歌啊啊啊"
  },
  "includes": {
    "media": [
      {
        "duration_ms": 7146,
        "height": 958,
        "media_key": "13_2057162511531573248",
        "preview_image_url": "https://pbs.twimg.com/amplify_video_thumb/2057162511531573248/img/eUien6LyeWZFqzuP.jpg",
        "public_metrics": {
          "view_count": 153
        },
        "type": "video",
        "variants": [
          {
            "bit_rate": 632000,
            "content_type": "video/mp4",
            "url": "https://video.twimg.com/amplify_video/2057162511531573248/vid/avc1/320x424/e7n9zzpSwCSZKTPo.mp4"
          },
          {
            "bit_rate": 950000,
            "content_type": "video/mp4",
            "url": "https://video.twimg.com/amplify_video/2057162511531573248/vid/avc1/480x638/kIuu-em9cuswTUG8.mp4"
          },
          {
            "bit_rate": 2176000,
            "content_type": "video/mp4",
            "url": "https://video.twimg.com/amplify_video/2057162511531573248/vid/avc1/720x958/GIK3s05Pdpylexcv.mp4"
          },
          {
            "content_type": "application/x-mpegURL",
            "url": "https://video.twimg.com/amplify_video/2057162511531573248/pl/EPtXJyF1n-Gh6Oqr.m3u8"
          }
        ],
        "width": 720
      }
    ],
    "tweets": [
      {
        "article": {},
        "attachments": {},
        "author_id": "1967234748704862208",
        "conversation_id": "2057162604854837441",
        "created_at": "2026-05-20T22:26:32.000Z",
        "edit_controls": {
          "editable_until": "2026-05-20T23:26:32.000Z",
          "edits_remaining": 5,
          "is_edit_eligible": false
        },
        "edit_history_tweet_ids": [
          "2057226496138420580"
        ],
        "entities": {
          "mentions": [
            {
              "end": 10,
              "id": "1944679199358570496",
              "start": 0,
              "username": "0kada_Mi0"
            }
          ]
        },
        "geo": {},
        "id": "2057226496138420580",
        "in_reply_to_user_id": "1944679199358570496",
        "lang": "zh",
        "note_tweet": {
          "entities": {}
        },
        "possibly_sensitive": false,
        "public_metrics": {
          "bookmark_count": 0,
          "impression_count": 0,
          "like_count": 0,
          "quote_count": 0,
          "reply_count": 0,
          "retweet_count": 0
        },
        "referenced_tweets": [
          {
            "id": "2057162604854837441",
            "type": "replied_to"
          }
        ],
        "reply_settings": "everyone",
        "text": "@0kada_Mi0 超级美 我好喜欢sasi这首歌啊啊啊"
      },
      {
        "article": {},
        "attachments": {
          "media_keys": [
            "13_2057162511531573248"
          ]
        },
        "author_id": "1944679199358570496",
        "conversation_id": "2057162604854837441",
        "created_at": "2026-05-20T18:12:39.000Z",
        "edit_controls": {
          "editable_until": "2026-05-20T19:12:39.000Z",
          "edits_remaining": 5,
          "is_edit_eligible": true
        },
        "edit_history_tweet_ids": [
          "2057162604854837441"
        ],
        "entities": {
          "urls": [
            {
              "display_url": "pic.x.com/QEz4nq9ml4",
              "end": 39,
              "expanded_url": "https://x.com/0kada_Mi0/status/2057162604854837441/video/1",
              "media_key": "13_2057162511531573248",
              "start": 16,
              "url": "https://t.co/QEz4nq9ml4"
            }
          ]
        },
        "geo": {},
        "id": "2057162604854837441",
        "lang": "zh",
        "note_tweet": {
          "entities": {}
        },
        "possibly_sensitive": false,
        "public_metrics": {
          "bookmark_count": 1,
          "impression_count": 488,
          "like_count": 19,
          "quote_count": 0,
          "reply_count": 4,
          "retweet_count": 0
        },
        "reply_settings": "everyone",
        "text": "超短裙 有光晕.. (⊙﹏⊙) https://t.co/QEz4nq9ml4"
      }
    ],
    "users": [
      {
        "created_at": "2025-09-14T14:31:42.000Z",
        "description": "欢迎互fo 当朋友圈刷 发碎碎念 什么都看 互关可以加微信 不聊黄 喜欢有礼貌的人 看到的基本上都回 欢迎找我聊天呀 小号@Yuri__ovo",
        "entities": {
          "description": {
            "mentions": [
              {
                "end": 71,
                "start": 61,
                "username": "Yuri__ovo"
              }
            ]
          }
        },
        "id": "1967234748704862208",
        "location": "你又来看我啦(*･ω･)ﾉ",
        "name": "yuri",
        "pinned_tweet_id": "2020195394265969020",
        "profile_image_url": "https://pbs.twimg.com/profile_images/1971968133637591045/valSqUne_normal.jpg",
        "protected": false,
        "public_metrics": {
          "followers_count": 141,
          "following_count": 379,
          "like_count": 3948,
          "listed_count": 0,
          "media_count": 42,
          "tweet_count": 964
        },
        "username": "yuri__ono",
        "verified": false
      },
      {
        "created_at": "2025-07-14T08:43:53.000Z",
        "description": "电子呕吐物\n06/碎碎念/brat/自伤od/高p\n想和女孩们互fo",
        "entities": {
          "url": {
            "urls": [
              {
                "display_url": "tellonym.me/user.miovo",
                "end": 23,
                "expanded_url": "https://tellonym.me/user.miovo",
                "start": 0,
                "url": "https://t.co/1hFCOSIfij"
              }
            ]
          }
        },
        "id": "1944679199358570496",
        "location": "纯绿🚪88",
        "name": "miovo",
        "pinned_tweet_id": "2035614009211408662",
        "profile_image_url": "https://pbs.twimg.com/profile_images/1944683149348175873/7SJk6K0n_normal.jpg",
        "protected": false,
        "public_metrics": {
          "followers_count": 1702,
          "following_count": 230,
          "like_count": 20028,
          "listed_count": 4,
          "media_count": 200,
          "tweet_count": 3149
        },
        "url": "https://t.co/1hFCOSIfij",
        "username": "0kada_Mi0",
        "verified": false
      }
    ]
  }
}