{
  "data": {
    "article": {},
    "attachments": {
      "media_keys": [
        "3_2057718597066403840"
      ],
      "media_source_tweet_id": [
        "2057718599587135615"
      ]
    },
    "author_id": "1967234748704862208",
    "conversation_id": "2057871322928316635",
    "created_at": "2026-05-22T17:08:51.000Z",
    "edit_controls": {
      "editable_until": "2026-05-22T18:08:51.000Z",
      "edits_remaining": 5,
      "is_edit_eligible": false
    },
    "edit_history_tweet_ids": [
      "2057871322928316635"
    ],
    "entities": {
      "mentions": [
        {
          "end": 13,
          "id": "2010357366466990080",
          "start": 3,
          "username": "Kyanu_tut"
        }
      ],
      "urls": [
        {
          "display_url": "pic.x.com/Nr4y3pcfs6",
          "end": 38,
          "expanded_url": "https://x.com/Kyanu_tut/status/2057718599587135615/photo/1",
          "media_key": "3_2057718597066403840",
          "start": 15,
          "url": "https://t.co/Nr4y3pcfs6"
        }
      ]
    },
    "geo": {},
    "id": "2057871322928316635",
    "lang": "zxx",
    "note_tweet": {
      "entities": {}
    },
    "possibly_sensitive": false,
    "public_metrics": {
      "bookmark_count": 0,
      "impression_count": 0,
      "like_count": 0,
      "quote_count": 0,
      "reply_count": 0,
      "retweet_count": 0
    },
    "referenced_tweets": [
      {
        "id": "2057718599587135615",
        "type": "retweeted"
      }
    ],
    "reply_settings": "everyone",
    "text": "RT @Kyanu_tut: https://t.co/Nr4y3pcfs6"
  },
  "includes": {
    "media": [
      {
        "height": 366,
        "media_key": "3_2057718597066403840",
        "public_metrics": {},
        "type": "photo",
        "url": "https://pbs.twimg.com/media/HI58KWnbsAAzNkT.jpg",
        "width": 550
      }
    ],
    "tweets": [
      {
        "article": {},
        "attachments": {
          "media_keys": [
            "3_2057718597066403840"
          ],
          "media_source_tweet_id": [
            "2057718599587135615"
          ]
        },
        "author_id": "1967234748704862208",
        "conversation_id": "2057871322928316635",
        "created_at": "2026-05-22T17:08:51.000Z",
        "edit_controls": {
          "editable_until": "2026-05-22T18:08:51.000Z",
          "edits_remaining": 5,
          "is_edit_eligible": false
        },
        "edit_history_tweet_ids": [
          "2057871322928316635"
        ],
        "entities": {
          "mentions": [
            {
              "end": 13,
              "id": "2010357366466990080",
              "start": 3,
              "username": "Kyanu_tut"
            }
          ],
          "urls": [
            {
              "display_url": "pic.x.com/Nr4y3pcfs6",
              "end": 38,
              "expanded_url": "https://x.com/Kyanu_tut/status/2057718599587135615/photo/1",
              "media_key": "3_2057718597066403840",
              "start": 15,
              "url": "https://t.co/Nr4y3pcfs6"
            }
          ]
        },
        "geo": {},
        "id": "2057871322928316635",
        "lang": "zxx",
        "note_tweet": {
          "entities": {}
        },
        "possibly_sensitive": false,
        "public_metrics": {
          "bookmark_count": 0,
          "impression_count": 0,
          "like_count": 0,
          "quote_count": 0,
          "reply_count": 0,
          "retweet_count": 0
        },
        "referenced_tweets": [
          {
            "id": "2057718599587135615",
            "type": "retweeted"
          }
        ],
        "reply_settings": "everyone",
        "text": "RT @Kyanu_tut: https://t.co/Nr4y3pcfs6"
      },
      {
        "article": {},
        "attachments": {
          "media_keys": [
            "3_2057718597066403840"
          ]
        },
        "author_id": "2010357366466990080",
        "conversation_id": "2057718599587135615",
        "created_at": "2026-05-22T07:01:59.000Z",
        "edit_controls": {
          "editable_until": "2026-05-22T08:01:59.000Z",
          "edits_remaining": 5,
          "is_edit_eligible": true
        },
        "edit_history_tweet_ids": [
          "2057718599587135615"
        ],
        "entities": {
          "urls": [
            {
              "display_url": "pic.x.com/Nr4y3pcfs6",
              "end": 23,
              "expanded_url": "https://x.com/Kyanu_tut/status/2057718599587135615/photo/1",
              "media_key": "3_2057718597066403840",
              "start": 0,
              "url": "https://t.co/Nr4y3pcfs6"
            }
          ]
        },
        "geo": {},
        "id": "2057718599587135615",
        "lang": "zxx",
        "note_tweet": {
          "entities": {}
        },
        "possibly_sensitive": false,
        "public_metrics": {
          "bookmark_count": 0,
          "impression_count": 360,
          "like_count": 9,
          "quote_count": 0,
          "reply_count": 1,
          "retweet_count": 0
        },
        "reply_settings": "everyone",
        "text": "https://t.co/Nr4y3pcfs6"
      }
    ],
    "users": [
      {
        "created_at": "2025-09-14T14:31:42.000Z",
        "description": "欢迎互fo 当朋友圈刷 发碎碎念 什么都看 互关可以加微信 不聊黄 喜欢有礼貌的人 看到的基本上都回 欢迎找我聊天呀 小号@Yuri__ovo",
        "entities": {
          "description": {
            "mentions": [
              {
                "end": 71,
                "start": 61,
                "username": "Yuri__ovo"
              }
            ]
          }
        },
        "id": "1967234748704862208",
        "location": "你又来看我啦(*･ω･)ﾉ",
        "name": "yuri",
        "pinned_tweet_id": "2020195394265969020",
        "profile_image_url": "https://pbs.twimg.com/profile_images/1971968133637591045/valSqUne_normal.jpg",
        "protected": false,
        "public_metrics": {
          "followers_count": 144,
          "following_count": 386,
          "like_count": 4029,
          "listed_count": 0,
          "media_count": 42,
          "tweet_count": 985
        },
        "username": "yuri__ono",
        "verified": false
      },
      {
        "created_at": "2026-01-11T14:25:51.000Z",
        "description": "这个精神病 表面上看起来 软软萌萌的 还用些萌不拉叽叽的头像 实际上是个暴力份子 谁敢相信？\n🚪28",
        "id": "2010357366466990080",
        "name": "精神病",
        "pinned_tweet_id": "2044984983928881623",
        "profile_image_url": "https://pbs.twimg.com/profile_images/2045722962678931456/2z1GHw2i_normal.jpg",
        "protected": false,
        "public_metrics": {
          "followers_count": 1562,
          "following_count": 414,
          "like_count": 732,
          "listed_count": 2,
          "media_count": 327,
          "tweet_count": 2120
        },
        "username": "Kyanu_tut",
        "verified": false
      }
    ]
  }
}