{
  "data": {
    "article": {},
    "attachments": {},
    "author_id": "1967234748704862208",
    "conversation_id": "2032490350594666627",
    "created_at": "2026-03-14T16:02:16.000Z",
    "edit_controls": {
      "editable_until": "2026-03-14T17:02:16.000Z",
      "edits_remaining": 5,
      "is_edit_eligible": false
    },
    "edit_history_tweet_ids": [
      "2032849803735089390"
    ],
    "entities": {
      "mentions": [
        {
          "end": 7,
          "id": "1671821091738886144",
          "start": 0,
          "username": "_04x_d"
        }
      ]
    },
    "geo": {},
    "id": "2032849803735089390",
    "in_reply_to_user_id": "1671821091738886144",
    "lang": "ja",
    "note_tweet": {
      "entities": {}
    },
    "possibly_sensitive": false,
    "public_metrics": {
      "bookmark_count": 0,
      "impression_count": 0,
      "like_count": 0,
      "quote_count": 0,
      "reply_count": 0,
      "retweet_count": 0
    },
    "referenced_tweets": [
      {
        "id": "2032490350594666627",
        "type": "replied_to"
      }
    ],
    "reply_settings": "everyone",
    "text": "@_04x_d 贱人"
  },
  "includes": {
    "media": [
      {
        "height": 2048,
        "media_key": "3_2032490342357123072",
        "public_metrics": {},
        "type": "photo",
        "url": "https://pbs.twimg.com/media/HDTbMqGbwAAOwRz.jpg",
        "width": 919
      }
    ],
    "tweets": [
      {
        "article": {},
        "attachments": {},
        "author_id": "1967234748704862208",
        "conversation_id": "2032490350594666627",
        "created_at": "2026-03-14T16:02:16.000Z",
        "edit_controls": {
          "editable_until": "2026-03-14T17:02:16.000Z",
          "edits_remaining": 5,
          "is_edit_eligible": false
        },
        "edit_history_tweet_ids": [
          "2032849803735089390"
        ],
        "entities": {
          "mentions": [
            {
              "end": 7,
              "id": "1671821091738886144",
              "start": 0,
              "username": "_04x_d"
            }
          ]
        },
        "geo": {},
        "id": "2032849803735089390",
        "in_reply_to_user_id": "1671821091738886144",
        "lang": "ja",
        "note_tweet": {
          "entities": {}
        },
        "possibly_sensitive": false,
        "public_metrics": {
          "bookmark_count": 0,
          "impression_count": 0,
          "like_count": 0,
          "quote_count": 0,
          "reply_count": 0,
          "retweet_count": 0
        },
        "referenced_tweets": [
          {
            "id": "2032490350594666627",
            "type": "replied_to"
          }
        ],
        "reply_settings": "everyone",
        "text": "@_04x_d 贱人"
      },
      {
        "article": {},
        "attachments": {
          "media_keys": [
            "3_2032490342357123072"
          ]
        },
        "author_id": "1671821091738886144",
        "conversation_id": "2032490350594666627",
        "created_at": "2026-03-13T16:13:56.000Z",
        "edit_controls": {
          "editable_until": "2026-03-13T17:13:56.000Z",
          "edits_remaining": 5,
          "is_edit_eligible": true
        },
        "edit_history_tweet_ids": [
          "2032490350594666627"
        ],
        "entities": {
          "urls": [
            {
              "display_url": "pic.x.com/BUQ3S4QSSB",
              "end": 27,
              "expanded_url": "https://x.com/_04x_d/status/2032490350594666627/photo/1",
              "media_key": "3_2032490342357123072",
              "start": 4,
              "url": "https://t.co/BUQ3S4QSSB"
            }
          ]
        },
        "geo": {},
        "id": "2032490350594666627",
        "lang": "zh",
        "note_tweet": {
          "entities": {}
        },
        "possibly_sensitive": false,
        "public_metrics": {
          "bookmark_count": 0,
          "impression_count": 2475,
          "like_count": 44,
          "quote_count": 0,
          "reply_count": 4,
          "retweet_count": 0
        },
        "reply_settings": "everyone",
        "text": "你媽的 https://t.co/BUQ3S4QSSB"
      }
    ],
    "users": [
      {
        "created_at": "2025-09-14T14:31:42.000Z",
        "description": "当朋友圈刷 发碎碎念 什么都看 女生可以加微信 不文爱不聊黄别来恶心我 喜欢有礼貌的人 看到的基本上都回",
        "id": "1967234748704862208",
        "name": "yu ri",
        "pinned_tweet_id": "2020195394265969020",
        "profile_image_url": "https://pbs.twimg.com/profile_images/1971968133637591045/valSqUne_normal.jpg",
        "protected": false,
        "public_metrics": {
          "followers_count": 52,
          "following_count": 261,
          "like_count": 1864,
          "listed_count": 0,
          "media_count": 23,
          "tweet_count": 424
        },
        "username": "yuri__ono",
        "verified": false
      },
      {
        "created_at": "2023-06-22T10:04:27.000Z",
        "description": "251 @_j14q1\n                                                                                         shtwt 只fo同类",
        "entities": {
          "description": {
            "mentions": [
              {
                "end": 11,
                "start": 4,
                "username": "_j14q1"
              }
            ]
          },
          "url": {
            "urls": [
              {
                "display_url": "ngl.link/yuki71720",
                "end": 23,
                "expanded_url": "https://ngl.link/yuki71720",
                "start": 0,
                "url": "https://t.co/Ex198DVgSE"
              }
            ]
          }
        },
        "id": "1671821091738886144",
        "name": "死体",
        "pinned_tweet_id": "2029973835861377248",
        "profile_image_url": "https://pbs.twimg.com/profile_images/2013525475642019840/pScrwFXD_normal.jpg",
        "protected": false,
        "public_metrics": {
          "followers_count": 936,
          "following_count": 367,
          "like_count": 10680,
          "listed_count": 1,
          "media_count": 436,
          "tweet_count": 2671
        },
        "url": "https://t.co/Ex198DVgSE",
        "username": "_04x_d",
        "verified": false
      }
    ]
  }
}